README.rst
setup.py
marbaloo_recaptcha/__init__.py
marbaloo_recaptcha/recaptcha.py
marbaloo_recaptcha.egg-info/PKG-INFO
marbaloo_recaptcha.egg-info/SOURCES.txt
marbaloo_recaptcha.egg-info/dependency_links.txt
marbaloo_recaptcha.egg-info/requires.txt
marbaloo_recaptcha.egg-info/top_level.txt