Metadata-Version: 1.1
Name: marbaloo-recaptcha
Version: 0.1.0
Summary: Google ReCaptcha for Cherrypy.
Home-page: http://github.com/marbaloo/marbaloo_recaptcha
Author: Mahdi Ghane.g
Author-email: UNKNOWN
License: MIT
Keywords: recaptcha cherrypy marbaloo marbaloo_recaptcha
Platform: UNKNOWN
Classifier: Development Status :: 3 - Alpha
Classifier: Intended Audience :: Developers
Classifier: Framework :: CherryPy
Classifier: License :: OSI Approved :: MIT License
Classifier: Operating System :: POSIX :: Linux
Classifier: Operating System :: Unix
Classifier: Programming Language :: Python :: 3 :: Only
Classifier: Topic :: Software Development :: Libraries
